{
  "id": "gen9championsvgc2026regma-2586942452",
  "format": "[Gen 9 Champions] VGC 2026 Reg M-A",
  "players": [
    "asfe3v",
    "dondillionare"
  ],
  "log": "|j|\u2606asfe3v\n|j|\u2606dondillionare\n|t:|1776474056\n|gametype|doubles\n|player|p1|asfe3v|266|1036\n|player|p2|dondillionare|mars|1083\n|gen|9\n|tier|[Gen 9 Champions] VGC 2026 Reg M-A\n|rated|\n|rule|Species Clause: Limit one of each Pok\u00e9mon\n|rule|Item Clause: Limit 1 of each item\n|clearpoke\n|poke|p1|Araquanid, L50, F|\n|poke|p1|Umbreon, L50, M|\n|poke|p1|Toxicroak, L50, F|\n|poke|p1|Sneasler, L50, F|\n|poke|p1|Venusaur, L50, F|\n|poke|p1|Slowking-Galar, L50, M|\n|poke|p2|Meganium, L50, F|\n|poke|p2|Pelipper, L50, F|\n|poke|p2|Archaludon, L50, M|\n|poke|p2|Sneasler, L50, F|\n|poke|p2|Mimikyu, L50, F|\n|poke|p2|Crabominable, L50, M|\n|teampreview|4\n|inactive|Battle timer is ON: inactive players will automatically lose when time's up. (requested by asfe3v)\n|inactive|dondillionare has 60 seconds left.\n|\n|t:|1776474118\n|teamsize|p1|4\n|teamsize|p2|4\n|start\n|switch|p1a: Slowking|Slowking-Galar, L50, M|100/100\n|switch|p1b: Umbreon|Umbreon, L50, M|100/100\n|switch|p2a: Mimikyu|Mimikyu, L50, F, shiny|100/100\n|switch|p2b: Crabominable|Crabominable, L50, M, shiny|100/100\n|turn|1\n|\n|t:|1776474142\n|detailschange|p2b: Crabominable|Crabominable-Mega, L50, M, shiny\n|-mega|p2b: Crabominable|Crabominable|Crabominite\n|move|p2a: Mimikyu|Shadow Claw|p2b: Crabominable\n|-crit|p2b: Crabominable\n|-damage|p2b: Crabominable|75/100\n|move|p1b: Umbreon|Focus Energy|p1b: Umbreon\n|-start|p1b: Umbreon|move: Focus Energy\n|move|p2b: Crabominable|Drain Punch|p1b: Umbreon\n|-supereffective|p1b: Umbreon|1\n|-enditem|p1b: Umbreon|Chople Berry|[eat]\n|-enditem|p1b: Umbreon|Chople Berry|[weaken]\n|-damage|p1b: Umbreon|58/100\n|-heal|p2b: Crabominable|100/100|[from] drain|[of] p1b: Umbreon\n|move|p1a: Slowking|Snarl|p2a: Mimikyu|[spread] p2a,p2b\n|-resisted|p2b: Crabominable|1\n|-activate|p2a: Mimikyu|ability: Disguise\n|-damage|p2a: Mimikyu|100/100\n|-damage|p2b: Crabominable|96/100\n|-unboost|p2a: Mimikyu|spa|1\n|-unboost|p2b: Crabominable|spa|1\n|detailschange|p2a: Mimikyu|Mimikyu-Busted, L50, F, shiny\n|-damage|p2a: Mimikyu|88/100|[from] pokemon: Mimikyu-Busted\n|\n|upkeep\n|turn|2\n|inactive|asfe3v has 30 seconds left.\n|inactive|dondillionare has 30 seconds left.\n|\n|t:|1776474167\n|move|p2b: Crabominable|Mach Punch|p1b: Umbreon\n|-supereffective|p1b: Umbreon|1\n|-damage|p1b: Umbreon|13/100\n|move|p1b: Umbreon|Baton Pass|p1b: Umbreon\n|\n|t:|1776474172\n|switch|p1b: Araquanid|Araquanid, L50, F|100/100|[from] Baton Pass\n|move|p2a: Mimikyu|Trick Room|p2a: Mimikyu\n|-fieldstart|move: Trick Room|[of] p2a: Mimikyu\n|move|p1a: Slowking|Trick Room|p1a: Slowking\n|-fieldend|move: Trick Room\n|\n|upkeep\n|turn|3\n|\n|t:|1776474195\n|switch|p2a: Pelipper|Pelipper, L50, F|100/100\n|-weather|RainDance|[from] ability: Drizzle|[of] p2a: Pelipper\n|switch|p1a: Toxicroak|Toxicroak, L50, F|100/100\n|move|p1b: Araquanid|Surf|p2b: Crabominable|[spread] p2a,p2b\n|-immune|p1a: Toxicroak|[from] ability: Dry Skin\n|-resisted|p2a: Pelipper|1\n|-crit|p2a: Pelipper\n|-crit|p2b: Crabominable\n|-damage|p2a: Pelipper|25/100\n|-damage|p2b: Crabominable|23/100\n|move|p2b: Crabominable|Iron Head|p1a: Toxicroak\n|-damage|p1a: Toxicroak|75/100\n|\n|-weather|RainDance|[upkeep]\n|-heal|p1a: Toxicroak|87/100|[from] ability: Dry Skin\n|-heal|p1a: Toxicroak|93/100|[from] item: Leftovers\n|upkeep\n|turn|4\n|\n|t:|1776474219\n|switch|p2b: Mimikyu|Mimikyu-Busted, L50, F, shiny|88/100\n|move|p1a: Toxicroak|Fake Out|p2a: Pelipper\n|-damage|p2a: Pelipper|13/100\n|cant|p2a: Pelipper|flinch\n|move|p1b: Araquanid|Surf|p2a: Pelipper|[spread] p2a,p2b\n|-heal|p1a: Toxicroak|100/100|[from] ability: Dry Skin|[of] p1b: Araquanid\n|-resisted|p2a: Pelipper|1\n|-crit|p2a: Pelipper\n|-crit|p2b: Mimikyu\n|-damage|p2a: Pelipper|0 fnt\n|-damage|p2b: Mimikyu|0 fnt\n|faint|p2a: Pelipper\n|faint|p2b: Mimikyu\n|\n|-weather|RainDance|[upkeep]\n|upkeep\n|c|\u2606dondillionare|nah surf araqwunid\n|c|\u2606dondillionare|u goit it bruh\n|inactive|dondillionare has 30 seconds left.\n|-message|dondillionare forfeited.\n|\n|win|asfe3v\n|raw|asfe3v's rating: 1036 &rarr; <strong>1075</strong><br />(+39 for winning)\n|raw|dondillionare's rating: 1083 &rarr; <strong>1058</strong><br />(-25 for losing)\n|l|\u2606dondillionare\n|player|p2|\n|l|\u2606asfe3v\n|player|p1|\n|j|\u2606dondillionare\n|player|p2|dondillionare|mars|\n",
  "uploadtime": 1776474254,
  "views": 20,
  "formatid": "gen9championsvgc2026regma",
  "rating": 1058,
  "private": 0,
  "password": null
}