{
  "id": "gen9championsvgc2026regma-2585784869",
  "format": "[Gen 9 Champions] VGC 2026 Reg M-A",
  "players": [
    "willidrako4",
    "LeoOmg"
  ],
  "log": "|j|\u2606willidrako4\n|j|\u2606LeoOmg\n|t:|1776370439\n|gametype|doubles\n|player|p1|willidrako4|102|1096\n|player|p2|LeoOmg|steven|1114\n|gen|9\n|tier|[Gen 9 Champions] VGC 2026 Reg M-A\n|rated|\n|rule|Species Clause: Limit one of each Pok\u00e9mon\n|rule|Item Clause: Limit 1 of each item\n|clearpoke\n|poke|p1|Glalie, L50, M|\n|poke|p1|Whimsicott, L50, M|\n|poke|p1|Politoed, L50, M|\n|poke|p1|Incineroar, L50, F|\n|poke|p1|Liepard, L50, M|\n|poke|p1|Primarina, L50, M|\n|poke|p2|Incineroar, L50, M|\n|poke|p2|Farigiraf, L50, F|\n|poke|p2|Golurk, L50|\n|poke|p2|Sneasler, L50, F|\n|poke|p2|Torkoal, L50, F|\n|poke|p2|Venusaur, L50, F|\n|teampreview|4\n|\n|t:|1776370468\n|teamsize|p1|4\n|teamsize|p2|4\n|start\n|switch|p1a: Glalie|Glalie, L50, M|100/100\n|switch|p1b: Whimsicott|Whimsicott, L50, M|100/100\n|switch|p2a: Farigiraf|Farigiraf, L50, F|100/100\n|switch|p2b: Sneasler|Sneasler, L50, F|100/100\n|turn|1\n|\n|t:|1776370491\n|detailschange|p1a: Glalie|Glalie-Mega, L50, M\n|-mega|p1a: Glalie|Glalie|Glalitite\n|move|p1b: Whimsicott|Tailwind|p1b: Whimsicott\n|-sidestart|p1: willidrako4|move: Tailwind\n|move|p1a: Glalie|Explosion|p2b: Sneasler|[spread] p1b,p2a,p2b\n|-supereffective|p1b: Whimsicott|1\n|-enditem|p1b: Whimsicott|Focus Sash\n|-damage|p1b: Whimsicott|1/100\n|-damage|p2a: Farigiraf|0 fnt\n|-damage|p2b: Sneasler|0 fnt\n|faint|p1a: Glalie\n|faint|p2a: Farigiraf\n|faint|p2b: Sneasler\n|\n|upkeep\n|inactive|Battle timer is ON: inactive players will automatically lose when time's up. (requested by LeoOmg)\n|\n|t:|1776370505\n|switch|p2b: Torkoal|Torkoal, L50, F|100/100\n|switch|p1a: Politoed|Politoed, L50, M|100/100\n|switch|p2a: Venusaur|Venusaur, L50, F|100/100\n|-weather|RainDance|[from] ability: Drizzle|[of] p1a: Politoed\n|-weather|SunnyDay|[from] ability: Drought|[of] p2b: Torkoal\n|turn|2\n|inactive|willidrako4 has 30 seconds left.\n|inactive|LeoOmg has 30 seconds left.\n|inactive|willidrako4 has 20 seconds left.\n|inactive|willidrako4 has 15 seconds left.\n|\n|t:|1776370548\n|move|p2b: Torkoal|Protect|p2b: Torkoal\n|-singleturn|p2b: Torkoal|Protect\n|move|p1b: Whimsicott|Memento|p2a: Venusaur\n|-unboost|p2a: Venusaur|atk|2\n|-unboost|p2a: Venusaur|spa|2\n|faint|p1b: Whimsicott\n|move|p2a: Venusaur|Giga Drain|p1a: Politoed\n|-supereffective|p1a: Politoed|1\n|-damage|p1a: Politoed|76/100\n|move|p1a: Politoed|Perish Song|p1a: Politoed\n|-start|p1a: Politoed|perish3|[silent]\n|-start|p2a: Venusaur|perish3|[silent]\n|-start|p2b: Torkoal|perish3|[silent]\n|-fieldactivate|move: Perish Song\n|\n|-weather|SunnyDay|[upkeep]\n|-heal|p1a: Politoed|82/100|[from] item: Leftovers\n|-start|p2a: Venusaur|perish3\n|-start|p1a: Politoed|perish3\n|-start|p2b: Torkoal|perish3\n|upkeep\n|\n|t:|1776370558\n|switch|p1b: Liepard|Liepard, L50, M|100/100\n|turn|3\n|inactive|LeoOmg has 30 seconds left.\n|\n|t:|1776370584\n|move|p1b: Liepard|Encore|p2b: Torkoal\n|-start|p2b: Torkoal|Encore\n|move|p2b: Torkoal|Protect|p2b: Torkoal\n|-singleturn|p2b: Torkoal|Protect\n|move|p2a: Venusaur|Giga Drain|p1b: Liepard\n|-damage|p1b: Liepard|72/100\n|move|p1a: Politoed|Substitute|p1a: Politoed\n|-start|p1a: Politoed|Substitute\n|-damage|p1a: Politoed|57/100\n|\n|-weather|SunnyDay|[upkeep]\n|-heal|p1a: Politoed|63/100|[from] item: Leftovers\n|-start|p2a: Venusaur|perish2\n|-start|p1a: Politoed|perish2\n|-start|p2b: Torkoal|perish2\n|upkeep\n|turn|4\n|-message|LeoOmg forfeited.\n|\n|win|willidrako4\n|raw|willidrako4's rating: 1096 &rarr; <strong>1123</strong><br />(+27 for winning)\n|raw|LeoOmg's rating: 1114 &rarr; <strong>1088</strong><br />(-26 for losing)\n|l|\u2606LeoOmg\n|player|p2|\n",
  "uploadtime": 1776370596,
  "views": 17,
  "formatid": "gen9championsvgc2026regma",
  "rating": 1088,
  "private": 0,
  "password": null
}